yuuki_core/TalkService.py
yuuki_core/__init__.py
yuuki_core/constants.py
yuuki_core/ttypes.py
yuuki_core-6.5.2.dist-info/DESCRIPTION.rst
yuuki_core-6.5.2.dist-info/METADATA
yuuki_core-6.5.2.dist-info/RECORD
yuuki_core-6.5.2.dist-info/WHEEL
yuuki_core-6.5.2.dist-info/metadata.json
yuuki_core-6.5.2.dist-info/top_level.txt
