Metadata-Version: 2.0
Name: yuuki-core
Version: 6.5.2
Summary: The LINE Protocol for Star Yuuki BOT
Home-page: https://gitlab.com/star-inc/yuuki_core
Author: Star Inc.
Author-email: "Star Inc." <star_inc@aol.com>
License: Mozilla Public License
Platform: UNKNOWN
Classifier: Development Status :: 5 - Production/Stable
Classifier: Environment :: Web Environment
Classifier: Intended Audience :: Developers
Classifier: License :: OSI Approved :: Mozilla Public License 2.0 (MPL 2.0)
Classifier: Operating System :: Microsoft :: Windows
Classifier: Operating System :: MacOS :: MacOS X
Classifier: Operating System :: POSIX
Classifier: Programming Language :: Python :: 3
Classifier: Topic :: Communications :: Chat
Classifier: Topic :: Software Development :: Libraries
Classifier: Topic :: Scientific/Engineering :: Interface Engine/Protocol Translator
Requires-Dist: thrift
